janus_client/__init__.py
janus_client/admin_monitor.py
janus_client/media.py
janus_client/message_transaction.py
janus_client/plugin_base.py
janus_client/plugin_echotest.py
janus_client/plugin_textroom.py
janus_client/plugin_video_call.py
janus_client/plugin_video_room.py
janus_client/session.py
janus_client/transport.py
janus_client/transport_http.py
janus_client/transport_websocket.py
janus_client/experiments/README.md
janus_client/experiments/media.py
janus_client/experiments/plugin_video_room_ffmpeg.py
janus_client/experiments/plugin_video_room_gst.py
janus_client-0.9.0.dist-info/METADATA
janus_client-0.9.0.dist-info/WHEEL
janus_client-0.9.0.dist-info/licenses/LICENSE
janus_client-0.9.0.dist-info/RECORD
