Metadata-Version: 2.4
Name: janus-client
Version: 0.9.0
Summary: Janus WebRTC gateway Python async client.
Project-URL: Repository, https://github.com/josephlim94/janus_gst_client_py
Author-email: Joseph Lim <josephlim_94@hotmail.co.uk>
License: MIT
License-File: LICENSE
Classifier: Development Status :: 4 - Beta
Classifier: License :: OSI Approved :: MIT License
Classifier: Operating System :: OS Independent
Classifier: Programming Language :: Python :: 3
Classifier: Programming Language :: Python :: 3.8
Classifier: Programming Language :: Python :: 3.9
Classifier: Programming Language :: Python :: 3.10
Classifier: Programming Language :: Python :: 3.11
Classifier: Programming Language :: Python :: 3.13
Classifier: Topic :: Software Development :: Libraries :: Python Modules
Requires-Python: <3.14,>=3.8
Requires-Dist: aiohttp>=3.8.5
Requires-Dist: aiortc>=1.5.0
Requires-Dist: websockets>=11.0.3
